skratch/__init__.py
skratch/__main__.py
skratch-0.1.0.dist-info/WHEEL
skratch-0.1.0.dist-info/METADATA
skratch-0.1.0.dist-info/RECORD
