Metadata-Version: 2.1
Name: skratch
Version: 0.1.0
Summary: Machine learning algorithms implemented from scratch
License: MIT
Author: Valentin Calomme
Author-email: info@valentincalomme.com
Requires-Python: >=3.7,<4.0
Classifier: License :: OSI Approved :: MIT License
Classifier: Programming Language :: Python :: 3
Classifier: Programming Language :: Python :: 3.7
Classifier: Programming Language :: Python :: 3.8
